LICENSE
MANIFEST.in
README
setup.py
django_timedeltafield.egg-info/PKG-INFO
django_timedeltafield.egg-info/SOURCES.txt
django_timedeltafield.egg-info/dependency_links.txt
django_timedeltafield.egg-info/top_level.txt
timedelta/VERSION
timedelta/__init__.py
timedelta/fields.py
timedelta/forms.py
timedelta/helpers.py
timedelta/models.py
timedelta/tests.py
timedelta/widgets.py
timedelta/templatetags/__init__.py
timedelta/templatetags/decimal_hours.py
timedelta/templatetags/timedelta.py